djextra/__init__.py
djextra/forms/__init__.py
djextra/forms/forms.py
djextra/forms/listfield.py
djextra/forms/angular1/__init__.py
djextra/forms/angular1/forms.py
djextra/forms/angular1/widgets/__init__.py
djextra/forms/angular1/widgets/base.py
djextra/forms/angular1/widgets/md_datepicker.py
djextra/forms/angular1/widgets/md_dateselect.py
djextra/forms/angular1/widgets/mdcheckbox.py
djextra/forms/angular1/widgets/mdmultiselect.py
djextra/forms/angular1/widgets/mdselect.py
djextra/forms/angular1/widgets/jinja2/attrs.html
djextra/forms/angular1/widgets/jinja2/md_checkbox.html
djextra/forms/angular1/widgets/jinja2/md_datepicker.html
djextra/forms/angular1/widgets/jinja2/md_select.html
djextra/forms/angular1/widgets/jinja2/md_select_option.html
tests/angular1/__init__.py
tests/angular1/widgets/__init__.py
tests/angular1/widgets/test_md_datepicker.py
tests/angular1/widgets/test_md_dateselect.py
tests/angular1/widgets/test_mdcheckbox.py
tests/angular1/widgets/test_mdmultiselect.py
tests/angular1/widgets/test_mdselect.py
djextra-1.1.6.dist-info/LICENSE.md
djextra-1.1.6.dist-info/METADATA
djextra-1.1.6.dist-info/WHEEL
djextra-1.1.6.dist-info/top_level.txt
djextra-1.1.6.dist-info/RECORD
