Metadata-Version: 2.1
Name: djextra
Version: 1.1.6
Summary: Additional Functions for Django
Home-page: https://github.com/hiroaki-yamamoto/djextra
Author: Hiroaki Yamamoto
Author-email: hiroaki@hysoftware.net
License: MIT
Keywords: Django
Platform: UNKNOWN
Classifier: License :: OSI Approved :: MIT License
Classifier: Framework :: Django :: 2.0
Requires-Dist: django (>=1.11)
Requires-Dist: jinja2
